<?xml version="1.0" encoding="UTF-8" standalone="no"?>
<results ResultsGenerationSearchTime="0:00:00.012" countResults="1" resultType="CVOAIRecordSearchService" searchTime="">
<visibility_rights>all</visibility_rights>
<notice>
<record>
<header>
<identifier>oai:bnf.fr:gallica/ark:/12148/bpt6k2006567</identifier>
<datestamp>2019-07-19</datestamp>
<setSpec>gallica:theme:8:84</setSpec>
<setSpec>gallica:typedoc:monographies</setSpec>
</header>
<metadata>
<oai_dc:dc xmlns:dc="http://purl.org/dc/elements/1.1/" xmlns:oai_dc="http://www.openarchives.org/OAI/2.0/oai_dc/" xmlns:xsi="http://www.w3.org/2001/XMLSchema-instance" xsi:schemaLocation="http://www.openarchives.org/OAI/2.0/oai_dc/ http://www.openarchives.org/OAI/2.0/oai_dc.xsd">
<dc:identifier>https://gallica.bnf.fr/ark:/12148/bpt6k2006567</dc:identifier>
<dc:title>Proverbes dramatiques : oeuvres complètes. 2e sér. / Théodore Leclercq</dc:title>
<dc:relation>Notice d'ensemble : http://catalogue.bnf.fr/ark:/12148/cb307665568</dc:relation>
<dc:creator>Leclercq, Théodore (1777-1851). Auteur du texte</dc:creator>
<dc:contributor>Sainte-Beuve, Charles-Augustin (1804-1869). Préfacier</dc:contributor>
<dc:contributor>Mérimée, Prosper (1803-1870). Préfacier</dc:contributor>
<dc:publisher> (Paris)</dc:publisher>
<dc:date>1852</dc:date>
<dc:format>4 vol. ; in-18</dc:format>
<dc:language>fre</dc:language>
<dc:language>français</dc:language>
<dc:relation>Notice du catalogue : http://catalogue.bnf.fr/ark:/12148/cb307665568</dc:relation>
<dc:type xml:lang="eng">text</dc:type>
<dc:type xml:lang="fre">monographie imprimée</dc:type>
<dc:type xml:lang="eng">monographie imprimée</dc:type>
<dc:source>Bibliothèque nationale de France</dc:source>
<dc:rights xml:lang="fre">domaine public</dc:rights>
<dc:rights xml:lang="eng">public domain</dc:rights>
</oai_dc:dc>
</metadata>
</record>
</notice>
<provenance>bnf.fr</provenance>
<sdewey>84</sdewey>
<dewey>8</dewey>
<source>Bibliothèque nationale de France</source>
<typedoc>monographie</typedoc>
<nqamoyen>97.71</nqamoyen>
<mode_indexation>text</mode_indexation>
<title>Proverbes dramatiques : oeuvres complètes. 2e sér. / Théodore Leclercq</title>
<date nbIssue="1">1852</date>
<first_indexation_date>15/10/2007</first_indexation_date>
<streamable>false</streamable>
</results>
