<?xml version="1.0" encoding="UTF-8" standalone="no"?>
<results ResultsGenerationSearchTime="0:00:00.014" countResults="1" resultType="CVOAIRecordSearchService" searchTime="">
<visibility_rights>all</visibility_rights>
<notice>
<record>
<header>
<identifier>oai:bnf.fr:gallica/ark:/12148/bpt6k57272782</identifier>
<datestamp>2018-04-26</datestamp>
<setSpec>gallica:corpus:PACA1</setSpec>
<setSpec>gallica:theme:9:944</setSpec>
<setSpec>gallica:typedoc:monographies</setSpec>
</header>
<metadata>
<oai_dc:dc xmlns:dc="http://purl.org/dc/elements/1.1/" xmlns:oai_dc="http://www.openarchives.org/OAI/2.0/oai_dc/" xmlns:xsi="http://www.w3.org/2001/XMLSchema-instance" xsi:schemaLocation="http://www.openarchives.org/OAI/2.0/oai_dc/ http://www.openarchives.org/OAI/2.0/oai_dc.xsd">
<dc:identifier>https://gallica.bnf.fr/ark:/12148/bpt6k57272782</dc:identifier>
<dc:title>Vérités historiques sur la royauté, suivies d'un dialogue entre un ouvrier républicain et un ouvrier légitimiste, dédié à la classe ouvrière par David Millaud,... avec une préface par Alphonse Esquiros,...</dc:title>
<dc:creator>Millaud, David. Auteur du texte</dc:creator>
<dc:contributor>Esquiros, Alphonse (1812-1876). Préfacier</dc:contributor>
<dc:publisher>Association d'ouvriers (Marseille)</dc:publisher>
<dc:date>1849</dc:date>
<dc:format>In-16, VIII-63 p.</dc:format>
<dc:language>fre</dc:language>
<dc:language>français</dc:language>
<dc:relation>Notice du catalogue : http://catalogue.bnf.fr/ark:/12148/cb30947302z</dc:relation>
<dc:type xml:lang="eng">text</dc:type>
<dc:type xml:lang="fre">monographie imprimée</dc:type>
<dc:type xml:lang="eng">monographie imprimée</dc:type>
<dc:source>Bibliothèque nationale de France, département Philosophie, histoire, sciences de l'homme, 8-LB55-2748</dc:source>
<dc:rights xml:lang="fre">domaine public</dc:rights>
<dc:rights xml:lang="eng">public domain</dc:rights>
<dc:description>Appartient à l’ensemble documentaire : PACA1</dc:description>
<dc:format>Nombre total de vues :  74</dc:format>
<dc:description>Avec mode texte</dc:description>
</oai_dc:dc>
</metadata>
</record>
</notice>
<provenance>bnf.fr</provenance>
<sdewey>944</sdewey>
<dewey>9</dewey>
<source>Bibliothèque nationale de France, département Philosophie, histoire, sciences de l'homme, 8-LB55-2748</source>
<typedoc>monographie</typedoc>
<nqamoyen>99.98</nqamoyen>
<mode_indexation>text</mode_indexation>
<title>Vérités historiques sur la royauté, suivies d'un dialogue entre un ouvrier républicain et un ouvrier légitimiste, dédié à la classe ouvrière par David Millaud,... avec une préface par Alphonse Esquiros,...</title>
<date nbIssue="1">1849</date>
<first_indexation_date>10/10/2009</first_indexation_date>
<streamable>false</streamable>
</results>
